<bill session="112" type="h" number="1178" updated="2011-03-30T06:23:33-04:00">
	<state datetime="2011-03-17">REFERRED</state>
	<status><introduced datetime="2011-03-17"/></status>

	<introduced datetime="2011-03-17"/>
	<titles>
		<title type="short" as="introduced">Disabled Veterans Commissary and Exchange Store Benefits Act</title>
		<title type="official" as="introduced">To amend title 10, United States Code, to extend military commissary and exchange store privileges to veterans with a compensable service-connected disability and to their dependents.</title>
	</titles>
	<sponsor id="400640"/>
	<cosponsors>
		<cosponsor id="412287" joined="2011-03-17"/>
		<cosponsor id="400244" joined="2011-03-17"/>
	</cosponsors>
	<actions>
		<action datetime="2011-03-17"><text>Referred to the House Committee on Armed Services.</text></action>
	</actions>
	<committees>
		<committee code="HSAS" name="House Armed Services" activity="Referral, In Committee" />
	</committees>
	<relatedbills>

	</relatedbills>
	<subjects>
		<term name="Armed forces and national security"/>
		<term name="Disability assistance"/>
		<term name="Military facilities and property"/>
		<term name="Veterans' pensions and compensation"/>
	</subjects>
	<amendments>

	</amendments>
	<summary>
	
	</summary>
</bill>
