<bill session="112" type="s" number="1136" updated="2011-06-14T06:33:33-04:00">
	<state datetime="2011-05-26">INTRODUCED</state>
	<status><introduced datetime="2011-05-26"/></status>

	<introduced datetime="2011-05-26"/>
	<titles>
		<title type="official" as="introduced">A bill to amend Public Law 106-206 to direct the Secretary of the Interior and the Secretary of Agriculture to require annual permits and assess annual fees for commercial filming activities on Federal land for film crews of 5 persons or fewer.</title>
	</titles>
	<sponsor id="412244"/>
	<cosponsors>

	</cosponsors>
	<actions>
		<action datetime="2011-05-26"><text>Read twice and referred to the Committee on Energy and Natural Resources.</text></action>
	</actions>
	<committees>
		<committee code="SSEG" name="Senate Energy and Natural Resources" activity="Referral, In Committee" />
	</committees>
	<relatedbills>

	</relatedbills>
	<subjects>

	</subjects>
	<amendments>

	</amendments>
	<summary>
	
	</summary>
</bill>
