<bill session="112" type="s" number="551" updated="2011-03-22T06:21:45-04:00">
	<state datetime="2011-03-10">INTRODUCED</state>
	<status><introduced datetime="2011-03-10"/></status>

	<introduced datetime="2011-03-10"/>
	<titles>
		<title type="short" as="introduced">Military Detainee Procedures Improvement Act of 2011</title>
		<title type="official" as="introduced">A bill to improve procedures for the detention and review of status of detainees of the United States in connection with the continuing armed conflict with al Qaeda, the Taliban, and affiliated groups.</title>
	</titles>
	<sponsor id="300071"/>
	<cosponsors>
		<cosponsor id="300021" joined="2011-03-10"/>
		<cosponsor id="412384" joined="2011-03-10"/>
		<cosponsor id="412493" joined="2011-03-10"/>
		<cosponsor id="300067" joined="2011-03-10"/>
		<cosponsor id="300047" joined="2011-03-10"/>
	</cosponsors>
	<actions>
		<action datetime="2011-03-10"><text>Read twice and referred to the Committee on Armed Services.</text></action>
	</actions>
	<committees>
		<committee code="SSAS" name="Senate Armed Services" activity="Referral, In Committee" />
	</committees>
	<relatedbills>

	</relatedbills>
	<subjects>
		<term name="Armed forces and national security"/>
		<term name="Caribbean area"/>
		<term name="Conflicts and wars"/>
		<term name="Congressional oversight"/>
		<term name="Correctional facilities and imprisonment"/>
		<term name="Criminal investigation, prosecution, interrogation"/>
		<term name="Criminal procedure and sentencing"/>
		<term name="Cuba"/>
		<term name="Defense spending"/>
		<term name="Detention of persons"/>
		<term name="Human rights"/>
		<term name="Intelligence activities, surveillance, classified information"/>
		<term name="International law and treaties"/>
		<term name="Latin America"/>
		<term name="Military facilities and property"/>
		<term name="Military operations and strategy"/>
		<term name="Presidents and presidential powers"/>
		<term name="Rule of law and government transparency"/>
		<term name="Terrorism"/>
	</subjects>
	<amendments>

	</amendments>
	<summary>
	
	</summary>
</bill>
