<bill session="112" type="s" number="768" updated="2011-04-26T06:13:12-04:00">
	<state datetime="2011-04-08">REPORTED</state>
	<status><calendar datetime="2011-04-08" /></status>

	<introduced datetime="2011-04-07"/>
	<titles>
		<title type="short" as="introduced">Government Shutdown Prevention Act of 2011</title>
		<title type="official" as="introduced">A bill to provide for continuing operations of Government in a fiscally responsible manner.</title>
	</titles>
	<sponsor id="412492"/>
	<cosponsors>
		<cosponsor id="400105" joined="2011-04-07"/>
	</cosponsors>
	<actions>
		<action datetime="2011-04-07"><text>Introduced in the Senate. Read the first time. Placed on Senate Legislative Calendar under Read the First Time.</text></action>
		<calendar datetime="2011-04-08"  state="REPORTED"><text>Read the second time. Placed on Senate Legislative Calendar under General Orders. Calendar No. 30.</text></calendar>
	</actions>
	<committees>

	</committees>
	<relatedbills>

	</relatedbills>
	<subjects>
		<term name="Economics and public finance"/>
		<term name="Appropriations"/>
		<term name="Budget deficits and national debt"/>
		<term name="Budget process"/>
		<term name="Defense spending"/>
		<term name="Department of Defense"/>
		<term name="Executive Office of the President"/>
		<term name="Executive agency funding and structure"/>
		<term name="Government employee pay, benefits, personnel management"/>
		<term name="Medicaid"/>
		<term name="Medicare"/>
		<term name="Members of Congress"/>
		<term name="Presidents and presidential powers"/>
		<term name="Social security and elderly assistance"/>
	</subjects>
	<amendments>

	</amendments>
	<summary>
	
	</summary>
</bill>
