<bill session="112" type="s" number="920" updated="2011-05-24T06:33:38-04:00">
	<state datetime="2011-05-09">INTRODUCED</state>
	<status><introduced datetime="2011-05-09"/></status>

	<introduced datetime="2011-05-09"/>
	<titles>
		<title type="short" as="introduced">SDHV Energy Efficiency Standards for America Act of 2011</title>
		<title type="official" as="introduced">A bill to create clean energy jobs and set efficiency standards for small-duct high-velocity air conditioning and heat pump systems, and for other purposes.</title>
	</titles>
	<sponsor id="400034"/>
	<cosponsors>
		<cosponsor id="300093" joined="2011-05-09"/>
		<cosponsor id="412243" joined="2011-05-09"/>
	</cosponsors>
	<actions>
		<action datetime="2011-05-09"><text>Read twice and referred to the Committee on Energy and Natural Resources.</text></action>
	</actions>
	<committees>
		<committee code="SSEG" name="Senate Energy and Natural Resources" activity="Referral, In Committee" />
	</committees>
	<relatedbills>
		<bill relation="unknown" session="112" type="h" number="1499" />
	</relatedbills>
	<subjects>
		<term name="Energy"/>
		<term name="Administrative law and regulatory procedures"/>
		<term name="Department of Energy"/>
		<term name="Energy efficiency and conservation"/>
		<term name="Lighting and heating"/>
	</subjects>
	<amendments>

	</amendments>
	<summary>
	
	</summary>
</bill>
